[
  {
    "name": "MODERNLOOP INC",
    "state": "CA",
    "year_incorporated": "2021",
    "nace": "5829",
    "employees": "18",
    "revenue_usd": 660000,
    "pl_before_tax": null,
    "total_assets": null,
    "equity": null,
    "website": "www.modernloop.com",
    "description": "Recruiting operations automation and streamlining platform operator",
    "contacts": [
      {
        "name": "Ms Lydia Han",
        "title": "President"
      }
    ]
  },
  {
    "name": "DEEPWELL DTX",
    "state": "WA",
    "year_incorporated": "2023",
    "nace": "5829",
    "employees": "10",
    "revenue_usd": 650000,
    "pl_before_tax": null,
    "total_assets": null,
    "equity": null,
    "website": "www.deepwelldtx.com",
    "description": null,
    "contacts": []
  },
  {
    "name": "MARIZYME INCORPORATED",
    "state": "FL",
    "year_incorporated": "2007",
    "nace": "5829",
    "employees": "11",
    "revenue_usd": 645810,
    "pl_before_tax": -65346920,
    "total_assets": 22015080,
    "equity": -4660640,
    "website": "www.marizyme.com",
    "description": "Marizyme, Inc. is a medical technology company. The Company is focused on cardiac and surgical care by delivering innovative solutions for coronary artery bypass graft (CABG) surgery and other surgical procedures. Its product DuraGraft, is a one-time intraoperative vascular graft treatment for use in vascular and bypass surgeries that maintains endothelial function and structure, thereby reducing the incidence and complications of graft failure and improving clinical outcomes post bypass surgery. The Company s product under development includes MATLOC and MAR-FG-001. MATLOC is a lab-on-chip digital screening and diagnostic device platform being developed for quantitative chronic kidney disease (CKD) assessment. The MAR-FG-001 is a tumescent solution base for fat grafting procedures that is used for plastic and cosmetic surgeries in which fat is transferred from one area of the body to another to correct a defect, replace injured tissue, or to make cosmetic enhancements.",
    "contacts": [
      {
        "name": "Dr. Vithalbhai Devashibhai Dhaduk",
        "title": "Independent Chairman of the Board"
      },
      {
        "name": "Dr. Vithalbhai Devashibhai Dhaduk",
        "title": "Dp"
      },
      {
        "name": "Mr James E Sapirstein",
        "title": "Chairman"
      },
      {
        "name": "Mr David L. Barthel",
        "title": "Chief Executive Officer, Secretary, Director; Director (Board of Directors)"
      },
      {
        "name": "Mr David L. Barthel",
        "title": "Member (Executive Management)"
      },
      {
        "name": "Mr David L. Barthel",
        "title": "Chief Executive Officer & SEC"
      },
      {
        "name": "Mr Terry Brostowin",
        "title": "Board of Dirs; Independent Director (Board of Directors)"
      },
      {
        "name": "Mr Neil J Campbell",
        "title": "President & Chief Executive Officer"
      },
      {
        "name": "Dr. William Hearl",
        "title": "Independent Director (Board of Directors)"
      },
      {
        "name": "Ms Julie Kampf",
        "title": "Independent Director (Board of Directors); Board of Dirs"
      },
      {
        "name": "Dr. Nilesh Patel",
        "title": "Independent Director (Board of Directors)"
      },
      {
        "name": "Mr Michael R. Stewart",
        "title": "Independent Director (Board of Directors); Board of Dirs"
      },
      {
        "name": "Mr Amar Dhaduk",
        "title": "Member (Executive Management)"
      },
      {
        "name": "Mr Amar Dhaduk",
        "title": "Director of Business Development"
      },
      {
        "name": "Mr George Kovalyov",
        "title": "Member (Executive Management)"
      },
      {
        "name": "Mr George Kovalyov",
        "title": "Chief Financial Officer, Treasurer"
      },
      {
        "name": "Dr. Catherine J. Pachuk",
        "title": "Member (Executive Management)"
      },
      {
        "name": "Dr. Catherine J. Pachuk",
        "title": "Chief Scientific Officer & Executive Vice President"
      },
      {
        "name": "Dr. Claudio Rigatto",
        "title": "Member (Executive Management)"
      },
      {
        "name": "Dr. Claudio Rigatto",
        "title": "Chief Medical OFFICER-MY Health Logic"
      },
      {
        "name": "Mr Harrison Ross",
        "title": "Member (Executive Management)"
      },
      {
        "name": "Mr Harrison Ross",
        "title": "Vice President of Finance"
      },
      {
        "name": "Mr Harrison Ross",
        "title": "Vice President, Finance"
      },
      {
        "name": "Mr Nicholas P Devito",
        "title": "Chief Executive Officer & Chief Financial Officer"
      },
      {
        "name": "Mr Gregg Nettleton",
        "title": "President & Chief Executive Officer"
      },
      {
        "name": "Mr Bruce H Harmon",
        "title": "Chief Financial Officer"
      },
      {
        "name": "Mr Roger Schaller",
        "title": "Executive Vice President - Commercial Operations"
      },
      {
        "name": "Mr Donald Very",
        "title": "Executive Vice President-R&D"
      },
      {
        "name": "Ms Amy Chandler",
        "title": "Executive Vice President - Regulatory & Quality Affairs"
      },
      {
        "name": "Mr Steven Andrew Brooks",
        "title": "Chief Medical Officer & Executive Vice President - Medical & Regulator"
      },
      {
        "name": "Dr. Vithalbhai Devashibhai Dhaduk",
        "title": "Chairman of the Board, Interim Chief Executive Officer"
      },
      {
        "name": "Dr. Vithalbhai Devashibhai Dhaduk",
        "title": "Chairman of the Board"
      },
      {
        "name": "Dr. Vithalbhai Devashibhai Dhaduk",
        "title": "Director"
      },
      {
        "name": "Dipl.-Kfm. Joerg Ott",
        "title": "Chairman of the Board, Chief Executive Officer"
      },
      {
        "name": "Mr James E Sapirstein",
        "title": "Chairman of the Board, Interim Chief Executive Officer"
      },
      {
        "name": "Mr James E Sapirstein",
        "title": "Director"
      },
      {
        "name": "Mr Stephen D Baksa",
        "title": "Independent Director"
      },
      {
        "name": "Mr David L. Barthel",
        "title": "Chief Executive Officer, Director"
      },
      {
        "name": "Mr David L. Barthel",
        "title": "Chief Executive Officer"
      },
      {
        "name": "Mr Terry Brostowin",
        "title": "Director"
      },
      {
        "name": "Mr Neil J Campbell",
        "title": "President, Chief Executive Officer, Director"
      },
      {
        "name": "Mr David M Darsch",
        "title": "Independent Director"
      },
      {
        "name": "Dr. William Hearl",
        "title": "Independent Director"
      },
      {
        "name": "Ms Julie Kampf",
        "title": "Independent Director"
      },
      {
        "name": "Mr John A Moore JR",
        "title": "Independent Director"
      },
      {
        "name": "Dr. Nilesh Patel",
        "title": "Director"
      },
      {
        "name": "Mr Mohammad A Shihadah",
        "title": "Independent Director"
      },
      {
        "name": "Mr Michael R. Stewart",
        "title": "Director"
      },
      {
        "name": "Mr George Kovalyov",
        "title": "Chief Financial Officer"
      },
      {
        "name": "Mr Nicholas P Devito",
        "title": "Interim Chief Executive Officer, Interim Chief Financial Officer"
      },
      {
        "name": "Mr Ralph Makar",
        "title": "President, Chief Executive Officer"
      },
      {
        "name": "Mr Markus Reiner Ernst",
        "title": "Chief Financial Officer, Principal Financial and Accounting Officer"
      },
      {
        "name": "Mr Bruce H Harmon",
        "title": "Chief Financial Officer"
      },
      {
        "name": "Mr Roger Schaller",
        "title": "Executive Vice President - Commercial Operations"
      },
      {
        "name": "Mr Donald Very",
        "title": "Executive Vice President - Research & Development"
      },
      {
        "name": "Ms Amy Chandler",
        "title": "Executive Vice President - Regulatory & Quality Affairs"
      },
      {
        "name": "Mr Steven Andrew Brooks",
        "title": "Executive Vice President - Medical and Regulatory Affairs, Chief Medical Officer"
      }
    ]
  },
  {
    "name": "RELIANT INFO SECURITY INC.",
    "state": "NY",
    "year_incorporated": "2012",
    "nace": "5829",
    "employees": "55",
    "revenue_usd": 640000,
    "pl_before_tax": null,
    "total_assets": null,
    "equity": null,
    "website": "www.reliantsecurity.com",
    "description": null,
    "contacts": [
      {
        "name": "Ms Roberta Gold",
        "title": "Office Manager"
      },
      {
        "name": "Ms Traci Weiner",
        "title": "Director of Finance and Administration"
      },
      {
        "name": "Mr Matthew Lewis",
        "title": "Sales & Marketing Coordinator"
      },
      {
        "name": "Ms Chloe Gage",
        "title": "Account Representative"
      },
      {
        "name": "Obrien Charles",
        "title": "Senior Engineer"
      },
      {
        "name": "Mr Tom Juliani",
        "title": "Information Technology Director"
      }
    ]
  },
  {
    "name": "COMETCHAT INC.",
    "state": "CO",
    "year_incorporated": null,
    "nace": "5829",
    "employees": "14",
    "revenue_usd": 640000,
    "pl_before_tax": null,
    "total_assets": null,
    "equity": null,
    "website": "www.cometchat.com",
    "description": "Web audio, video and chat customer communication software developer",
    "contacts": [
      {
        "name": "Mr Anant Garg",
        "title": "President"
      },
      {
        "name": "Mr Anant Garg",
        "title": "Founder & Chief Technology Officer"
      },
      {
        "name": "Mr Anuj Garg",
        "title": "Chief Executive Officer & Co-Founder"
      },
      {
        "name": "Mr Amit Thaker",
        "title": "Account Executive"
      },
      {
        "name": "Ben Dewberry",
        "title": "Solutions Consultant"
      }
    ]
  },
  {
    "name": "FIRST MILE GROUP, INC.",
    "state": "NY",
    "year_incorporated": "2019",
    "nace": "5829",
    "employees": "270",
    "revenue_usd": 640000,
    "pl_before_tax": null,
    "total_assets": null,
    "equity": null,
    "website": "www.alloy.com",
    "description": "Data-driven verification platform operator",
    "contacts": [
      {
        "name": "Mr Thomas Nicholas",
        "title": "Chief Executive Officer"
      },
      {
        "name": "Ms Jennifer Stone",
        "title": "Mrs"
      }
    ]
  },
  {
    "name": "TYME GLOBAL TECHNOLOGIES, LLC",
    "state": "NY",
    "year_incorporated": "2022",
    "nace": "5829",
    "employees": "75",
    "revenue_usd": 640000,
    "pl_before_tax": null,
    "total_assets": null,
    "equity": null,
    "website": "www.tymeglobal.com",
    "description": null,
    "contacts": [
      {
        "name": "Cristescu David",
        "title": "Member"
      },
      {
        "name": "Henschen Lori",
        "title": "Member"
      },
      {
        "name": "Levin Ryan",
        "title": "Member"
      }
    ]
  },
  {
    "name": "BEACON PLATFORM INCORPORATED",
    "state": "NY",
    "year_incorporated": "2016",
    "nace": "5829",
    "employees": "60",
    "revenue_usd": 640000,
    "pl_before_tax": null,
    "total_assets": null,
    "equity": null,
    "website": "www.beacon.io",
    "description": "Cloud-based trading Software-as-a-Service (SaaS) provider",
    "contacts": [
      {
        "name": "Mr Mark Gregory Higgins",
        "title": "Chairman"
      },
      {
        "name": "Mr Mark Gregory Higgins",
        "title": "Co-Founder and Chief Operating Officer"
      },
      {
        "name": "Mr Kirat Singh",
        "title": "Chairman"
      },
      {
        "name": "Mr Kirat Singh",
        "title": "Chief Executive Officer (Ceo); Co-Founder and Chief Executive Officer"
      },
      {
        "name": "Mr Mark Ayzenberg",
        "title": "Director of Business Development"
      },
      {
        "name": "Lk Tan",
        "title": "Head of Finance"
      },
      {
        "name": "Mr Viktor Ziskin",
        "title": "Co-Head of Banking"
      },
      {
        "name": "Ms Anya Boutov",
        "title": "Head of Sales, Director"
      },
      {
        "name": "Mr Matt Murphy",
        "title": "Senior Commercial Counsel"
      },
      {
        "name": "Mr Alan Roberts",
        "title": "Dev Operations Engineer"
      },
      {
        "name": "Mr Shuai Xue",
        "title": "Quant"
      },
      {
        "name": "Mr Mark Gregory Higgins",
        "title": "Chief Financial Officer"
      }
    ]
  },
  {
    "name": "TOWERCARE TECHNOLOGIES, INC.",
    "state": "PA",
    "year_incorporated": "2007",
    "nace": "5829",
    "employees": "11",
    "revenue_usd": 639000,
    "pl_before_tax": null,
    "total_assets": null,
    "equity": null,
    "website": "www.towercare.com",
    "description": null,
    "contacts": [
      {
        "name": "Ms Donna Myers",
        "title": "President"
      },
      {
        "name": "Ms Gina Davis",
        "title": "Implementation Specialist"
      }
    ]
  },
  {
    "name": "ECLIPSE DIGITAL IMAGING, INC.",
    "state": "SD",
    "year_incorporated": "1998",
    "nace": "5829",
    "employees": "12",
    "revenue_usd": 630000,
    "pl_before_tax": null,
    "total_assets": null,
    "equity": null,
    "website": "www.presentermedia.com",
    "description": null,
    "contacts": [
      {
        "name": "Mr Art Holden",
        "title": "Owner"
      },
      {
        "name": "Ms Kiara L Jones",
        "title": "Corporate Communications"
      },
      {
        "name": "Mr Mike Weber",
        "title": "Corporate Communications"
      },
      {
        "name": "Mr Greg Wilson",
        "title": "Animator / Photographer"
      }
    ]
  },
  {
    "name": "AZUL & CO",
    "state": "FL",
    "year_incorporated": null,
    "nace": "5829",
    "employees": "16",
    "revenue_usd": 630000,
    "pl_before_tax": null,
    "total_assets": null,
    "equity": null,
    "website": "www.azul.com",
    "description": null,
    "contacts": []
  },
  {
    "name": "SPARQ SOLUTIONS INC.",
    "state": "MI",
    "year_incorporated": "2018",
    "nace": "5829",
    "employees": "12",
    "revenue_usd": 630000,
    "pl_before_tax": null,
    "total_assets": null,
    "equity": null,
    "website": "www.sparq.solutions",
    "description": null,
    "contacts": [
      {
        "name": "Ms Prema Ramakrishnan",
        "title": "President"
      }
    ]
  },
  {
    "name": "INTERCOM TRAINING, INC.",
    "state": "TX",
    "year_incorporated": "1988",
    "nace": "5829",
    "employees": "12",
    "revenue_usd": 624000,
    "pl_before_tax": null,
    "total_assets": null,
    "equity": null,
    "website": "www.intercom-interactive.com",
    "description": null,
    "contacts": [
      {
        "name": "Ms Karen Mcguire",
        "title": "Project Manager"
      }
    ]
  },
  {
    "name": "LTG PLC",
    "state": "NC",
    "year_incorporated": "2008",
    "nace": "5829",
    "employees": "330",
    "revenue_usd": 610000,
    "pl_before_tax": null,
    "total_assets": null,
    "equity": null,
    "website": "peoplefluent.com",
    "description": null,
    "contacts": [
      {
        "name": "Ms Sharyn Ellerbe",
        "title": "Paralegal"
      }
    ]
  },
  {
    "name": "THE ADVANTAGE SOFTWARE COMPANY, LLC",
    "state": "NC",
    "year_incorporated": "1998",
    "nace": "5829",
    "employees": "32",
    "revenue_usd": 610000,
    "pl_before_tax": null,
    "total_assets": null,
    "equity": null,
    "website": "www.gotoadvantage.com",
    "description": null,
    "contacts": [
      {
        "name": "Mr Arthur Lacerte",
        "title": "Chairman"
      },
      {
        "name": "Ms Ellen Doreen Coulter",
        "title": "Chief Executive Officer"
      },
      {
        "name": "Mr Michael John Byrnes",
        "title": "Vice President"
      },
      {
        "name": "Mr Scott Byrnes",
        "title": "Secretary"
      },
      {
        "name": "Ms Susan Lacerte",
        "title": "Secretary"
      },
      {
        "name": "Dominique Lacerte",
        "title": "Business Development / Sales"
      },
      {
        "name": "Mr Michael August Coulter",
        "title": "Controller"
      },
      {
        "name": "Mr Mike Mcgee",
        "title": "Vice President Sales and Marketing"
      },
      {
        "name": "Courtney Boydston",
        "title": "Sales Representative"
      },
      {
        "name": "Ms Colleen Schwab",
        "title": "Media Product Manager"
      },
      {
        "name": "Mr Dan DeBartolo",
        "title": "Director, Client Services"
      },
      {
        "name": "Ms Tina Hussion",
        "title": "Director, Client Relations"
      },
      {
        "name": "Ms Carol Robinson",
        "title": "Client Services Specialist"
      },
      {
        "name": "Mr Steven Walden",
        "title": "Director Software Engineering"
      },
      {
        "name": "Mr Rich Flanigan",
        "title": "Technical Support Supervisor"
      },
      {
        "name": "Mr Wolfgang Ring",
        "title": "Technology Support Specialist"
      },
      {
        "name": "Mr Leslie Heller",
        "title": "Quality Assurance Manager"
      },
      {
        "name": "Ms Chastity Burrell",
        "title": "Director of Software Services"
      },
      {
        "name": "Ms Deirdre Doyle",
        "title": "Information Technology Director"
      },
      {
        "name": "Ms Deirdre Doyle",
        "title": "Senior Software Support Specialist"
      },
      {
        "name": "Mr Rick Beauvais",
        "title": "It Analyst; Information Technology Analyst"
      },
      {
        "name": "Mr Mike Christman",
        "title": "Senior Software Engineer"
      },
      {
        "name": "Ms Claudia Newbrough",
        "title": "Software Support"
      },
      {
        "name": "Jondren Swann",
        "title": "Software Support"
      },
      {
        "name": "Mr Jeff Thrall",
        "title": "Advantage Software"
      },
      {
        "name": "Dreama Johnsen",
        "title": "Senior Support Specialist"
      },
      {
        "name": "Mr Joseph Reynolds",
        "title": "Consultant"
      }
    ]
  },
  {
    "name": "FEEDTRAIL INC.",
    "state": "NC",
    "year_incorporated": "2021",
    "nace": "5829",
    "employees": "17",
    "revenue_usd": 610000,
    "pl_before_tax": null,
    "total_assets": null,
    "equity": null,
    "website": "www.feedtrail.com",
    "description": "Healthcare patients feedback platform operator",
    "contacts": [
      {
        "name": "Mr Paul Jaglowski",
        "title": "Co-Founder, Chief Executive Officer"
      },
      {
        "name": "Krafft Kay",
        "title": "Chief Executive Officer"
      },
      {
        "name": "Alexander Stephanie",
        "title": "Chief Executive Officer"
      },
      {
        "name": "Mr Mikko Lauri Juhani Lehmus",
        "title": "Co-Founder & Head of Product"
      },
      {
        "name": "Mr Chris Miller",
        "title": "Head of Sales, Co-Founder"
      },
      {
        "name": "Mr Gert Olavi Volmer",
        "title": "Co-Founder & Chief Marketing Officer"
      },
      {
        "name": "Hayne James",
        "title": "Chief Financial Officer"
      },
      {
        "name": "Madison Boley",
        "title": "Sales Operations Manager"
      },
      {
        "name": "Mr Kendall Massey",
        "title": "Sales Operations Manager"
      },
      {
        "name": "Mr Brian Ligett",
        "title": "U.S. Sales"
      },
      {
        "name": "Mr Robert Delk",
        "title": "Senior Account Executive"
      },
      {
        "name": "Mr Ryan Phillips",
        "title": "Director of Customer Success"
      },
      {
        "name": "Mr Owen Will",
        "title": "Account Executive"
      },
      {
        "name": "Mr Bradley Mcclure",
        "title": "Customer Success Manager"
      },
      {
        "name": "Mr Andy Roth",
        "title": "Manager, Customer Success"
      },
      {
        "name": "Ms Vera Delphis",
        "title": "Analytics & Business Intelligence Head of Data"
      }
    ]
  },
  {
    "name": "PROVIDERLINK",
    "state": "NC",
    "year_incorporated": "2001",
    "nace": "5829",
    "employees": "30",
    "revenue_usd": 610000,
    "pl_before_tax": null,
    "total_assets": null,
    "equity": null,
    "website": "www.providerlink.com",
    "description": "Communications management technology solutions provider for the healthcare industry",
    "contacts": []
  },
  {
    "name": "ARCH TECHNOLOGY SOLUTIONS LLC",
    "state": "OK",
    "year_incorporated": "2018",
    "nace": "5829",
    "employees": "25",
    "revenue_usd": 610000,
    "pl_before_tax": null,
    "total_assets": null,
    "equity": null,
    "website": "www.archtechus.com",
    "description": null,
    "contacts": []
  },
  {
    "name": "ROLE MODEL SOTWARE INC",
    "state": "NC",
    "year_incorporated": "2015",
    "nace": "5829",
    "employees": "30",
    "revenue_usd": 610000,
    "pl_before_tax": null,
    "total_assets": null,
    "equity": null,
    "website": "www.rolemodelsoftware.com",
    "description": null,
    "contacts": []
  },
  {
    "name": "MAGNUS HEALTH TECHNOLOGY INC",
    "state": "NC",
    "year_incorporated": "2013",
    "nace": "5829",
    "employees": "35",
    "revenue_usd": 610000,
    "pl_before_tax": null,
    "total_assets": null,
    "equity": null,
    "website": "www.magnushealth.com",
    "description": "Student medical record software developer",
    "contacts": [
      {
        "name": "Mr Brian Biddulph Krentar",
        "title": "Chief Executive Officer"
      },
      {
        "name": "Mr Allen Cobb",
        "title": "Secretary"
      },
      {
        "name": "Mr Melany Cave",
        "title": "Director, Sales"
      },
      {
        "name": "Mr Dino Skerlos",
        "title": "Director of Sales"
      },
      {
        "name": "Ms Morgan Miller",
        "title": "Sales Development"
      },
      {
        "name": "Inese Hoover",
        "title": "Director, Marketing"
      },
      {
        "name": "Ms Marlene Chotkowski",
        "title": "Digital Marketing Specialist"
      },
      {
        "name": "Ms Amber Hawkins",
        "title": "Account Executive"
      },
      {
        "name": "Ms Janet Jaramillo",
        "title": "Account Executive"
      },
      {
        "name": "Mr Wes Maples",
        "title": "Account Executive"
      },
      {
        "name": "Ms Kerri Wade",
        "title": "Client Success Specialist"
      },
      {
        "name": "Mr Scott Pollak",
        "title": "CTO"
      },
      {
        "name": "Ms Martika Hedgepeth",
        "title": "Regional Manager"
      },
      {
        "name": "Ms Jazmine Scurlock",
        "title": "Regional Project Manager"
      },
      {
        "name": "Ms Irina Simatova",
        "title": "Manager, Quality Assurance"
      },
      {
        "name": "Mr Zachary Ritz",
        "title": "Quality Assurance Analyst"
      },
      {
        "name": "Ms Aliya Farheen",
        "title": "Software Engineer"
      },
      {
        "name": "Mr Kevin Lavigne",
        "title": "Software Developer"
      },
      {
        "name": "Mr Blake Lee",
        "title": "Software Developer"
      },
      {
        "name": "Ms Lindsey Miller",
        "title": "Business Analyst"
      },
      {
        "name": "Mr Charles R Scarantino",
        "title": "Governing Person"
      }
    ]
  },
  {
    "name": "JUNXURE",
    "state": "NC",
    "year_incorporated": null,
    "nace": "5829",
    "employees": "46",
    "revenue_usd": 610000,
    "pl_before_tax": null,
    "total_assets": null,
    "equity": null,
    "website": "www.junxure.com",
    "description": null,
    "contacts": [
      {
        "name": "Mr Greg Friedman",
        "title": "President"
      },
      {
        "name": "Mr Ken Golding",
        "title": "Vice President"
      },
      {
        "name": "Mr John Shangler",
        "title": "Executive Vice President"
      },
      {
        "name": "Ms Charleen Fragomeni",
        "title": "Administrative Assistant"
      },
      {
        "name": "Mr Robert Defrancis",
        "title": "Director of Sales"
      },
      {
        "name": "Ms Louise Stafford",
        "title": "Marketing Specialist"
      },
      {
        "name": "Chen Chiu",
        "title": "Technical Support Analyst"
      },
      {
        "name": "Mr Ryan Cross",
        "title": "Technical Support Specialist"
      },
      {
        "name": "Mr Aaron Donnelly",
        "title": "Technical Support Specialist"
      },
      {
        "name": "Mr Adam Fryor",
        "title": "Technical Support Specialist"
      },
      {
        "name": "Mr Jamar Green",
        "title": "Technical Support Specialist"
      },
      {
        "name": "Ms Heidi Gury",
        "title": "Software Quality Assurance Engineer (via Robert Half Technology)"
      },
      {
        "name": "Mr David Bogar",
        "title": "Information Technology Manager"
      },
      {
        "name": "Mr Elliot Lochansky",
        "title": "Data Conversion Specialist"
      },
      {
        "name": "Mr Duane Burnett",
        "title": "Business Analyst"
      },
      {
        "name": "Mr John Haas",
        "title": "Consultant"
      }
    ]
  },
  {
    "name": "ICLOGIC INC",
    "state": "NC",
    "year_incorporated": "1996",
    "nace": "5829",
    "employees": "50",
    "revenue_usd": 610000,
    "pl_before_tax": null,
    "total_assets": null,
    "equity": null,
    "website": "www.usatcorp.com",
    "description": "Stocking distributor of top-tier cellular modems, cellular gateways, cellular routers, and ruggedized managed and unmanaged switches designed for critical infrastructure applications",
    "contacts": []
  },
  {
    "name": "RHYTHM SYSTEMS, INC.",
    "state": "NC",
    "year_incorporated": "2006",
    "nace": "5829",
    "employees": "25",
    "revenue_usd": 610000,
    "pl_before_tax": null,
    "total_assets": null,
    "equity": null,
    "website": "www.rhythmsystems.com",
    "description": null,
    "contacts": [
      {
        "name": "Mr Thean Patrick",
        "title": "Chief Executive Officer"
      },
      {
        "name": "Ms Cindy Praeger",
        "title": "Founder"
      },
      {
        "name": "Shelby Casabura",
        "title": "Strategy Operations"
      },
      {
        "name": "Ms Melissa Perna",
        "title": "Controller"
      },
      {
        "name": "Ms Jessica Wishart",
        "title": "Training & Innovation Manager"
      },
      {
        "name": "Ms Michelle Cras",
        "title": "Senior Digital Marketing Specialist"
      },
      {
        "name": "Mr Meagan Griffith",
        "title": "Client Services Coordinator"
      },
      {
        "name": "Mr Ryan Walcott",
        "title": "Head of Products"
      },
      {
        "name": "Mr Paige Wilcox",
        "title": "Execution Coach"
      }
    ]
  },
  {
    "name": "WEAVEUP, INC.",
    "state": "NC",
    "year_incorporated": "2015",
    "nace": "5829",
    "employees": "17",
    "revenue_usd": 610000,
    "pl_before_tax": null,
    "total_assets": null,
    "equity": null,
    "website": "www.weaveup.com",
    "description": null,
    "contacts": [
      {
        "name": "Mr Michael J Dobin",
        "title": "Chairperson of the Board"
      },
      {
        "name": "Ms Diana Kauppinen",
        "title": "Chairperson of the Board"
      },
      {
        "name": "Mr Flint Davis",
        "title": "President"
      },
      {
        "name": "Mr Davis James",
        "title": "President"
      },
      {
        "name": "Mr Wade D. Miquelon",
        "title": "Chief Executive Officer"
      },
      {
        "name": "Mr Matthew Susz",
        "title": "Vice President"
      },
      {
        "name": "Aber Ann",
        "title": "Secretary"
      },
      {
        "name": "Mr Steve De Santis",
        "title": "Corporate Secretary"
      },
      {
        "name": "Ms Renee Jefferson",
        "title": "Treasurer"
      }
    ]
  },
  {
    "name": "WE LOVE KIDS, INC.",
    "state": "VA",
    "year_incorporated": "2009",
    "nace": "5829",
    "employees": "14",
    "revenue_usd": 600000,
    "pl_before_tax": null,
    "total_assets": null,
    "equity": null,
    "website": "www.welovekidsinc.com",
    "description": null,
    "contacts": [
      {
        "name": "Ms Adrianne Childs",
        "title": "Owner"
      },
      {
        "name": "Mr Thomas R Heflin",
        "title": "Vice President"
      },
      {
        "name": "Ms Gwendolyn Heflin",
        "title": "Officer"
      }
    ]
  }
]